<T3DataStructure>
	<meta>
		<langDisable>1</langDisable>
	</meta>
	<sheets>
		<main>
			<ROOT>
				<TCEforms>
					<sheetTitle>LLL:EXT:entity_bicycle_market/Resources/Private/Language/locallang_plugin.xlf:flexform.sheet.main</sheetTitle>
				</TCEforms>
				<type>array</type>
				<el>
					<settings.showPageUid>
						<TCEforms>
							<label>LLL:EXT:entity_bicycle_market/Resources/Private/Language/locallang_plugin.xlf:flexform.field.show-page-uid</label>
							<config>
								<type>group</type>
								<internal_type>db</internal_type>
								<allowed>pages</allowed>
								<size>1</size>
								<minitems>0</minitems>
								<maxitems>1</maxitems>
							</config>
						</TCEforms>
					</settings.showPageUid>
					<settings.requestPageUid>
						<TCEforms>
							<label>LLL:EXT:entity_bicycle_market/Resources/Private/Language/locallang_plugin.xlf:flexform.field.request-page-uid</label>
							<config>
								<type>group</type>
								<internal_type>db</internal_type>
								<allowed>pages</allowed>
								<size>1</size>
								<minitems>0</minitems>
								<maxitems>1</maxitems>
							</config>
						</TCEforms>
					</settings.requestPageUid>
					<settings.formContentUid>
						<TCEforms>
							<label>LLL:EXT:entity_bicycle_market/Resources/Private/Language/locallang_plugin.xlf:flexform.field.form-content-uid</label>
							<config>
								<type>group</type>
								<internal_type>db</internal_type>
								<allowed>tt_content</allowed>
								<size>1</size>
								<minitems>0</minitems>
								<maxitems>1</maxitems>
							</config>
						</TCEforms>
					</settings.formContentUid>
				</el>
			</ROOT>
		</main>
	</sheets>
</T3DataStructure>